reaction_metrics_exporter/__init__.py
reaction_metrics_exporter/__main__.py
reaction_metrics_exporter/app.py
reaction_metrics_exporter/handler.py
reaction_metrics_exporter/models/config.py
reaction_metrics_exporter/models/event.py
reaction_metrics_exporter/models/exception.py
reaction_metrics_exporter/models/log.py
reaction_metrics_exporter/models/metric.py
reaction_metrics_exporter/reaction.py
reaction_metrics_exporter/reader.py
reaction_metrics_exporter/state.py
reaction_metrics_exporter/transformer.py
reaction_metrics_exporter-1.0.0.dist-info/LICENSE
reaction_metrics_exporter-1.0.0.dist-info/METADATA
reaction_metrics_exporter-1.0.0.dist-info/WHEEL
reaction_metrics_exporter-1.0.0.dist-info/RECORD
