Metadata-Version: 2.3
Name: reaction-metrics-exporter
Version: 1.0.0
Summary: A daemon that scans reaction outputs, and serves an HTTP OpenMetrics endpoint
License: AGPL-3.0-or-later
Keywords: reaction,prometheus,openmetrics
Author: Lilou
Author-email: lilou@chosto.me
Requires-Python: >=3.10
Classifier: Development Status :: 4 - Beta
Classifier: Topic :: System :: Monitoring
Requires-Dist: aiofiles (>=24.1.0,<25.0.0)
Requires-Dist: aionotify (>=0.3.1,<0.4.0)
Requires-Dist: asyncio-simple-http-server (>=0.0.8,<0.0.9)
Requires-Dist: jinja2 (>=3.1.6,<4.0.0)
Requires-Dist: prometheus-client (>=0.22.1,<0.23.0)
Requires-Dist: pytest (>=8.4.1,<9.0.0)
Requires-Dist: python-dateutil (>=2.9.0.post0,<3.0.0)
Requires-Dist: python-systemd (>=0.0.9,<0.0.10)
Requires-Dist: ruamel-yaml (>=0.18.14,<0.19.0)
Requires-Dist: schema (>=0.7.7,<0.8.0)
Requires-Dist: structlog (>=25.4.0,<26.0.0)
Requires-Dist: systemd-python (>=235,<236)
